{
    "gametype": 1,
    "gamedescription": "¿Cuáles son similares?",
    "gamedisplaymatch": "title",
    "gamedroptype": "buildDroptype1",
    "directory": "gallery-01",
    "completed": false,
    "gallery": [
        { 
            "qn": "11 + 11",
            "awr": "22",
            "id": "001",
            "matched": false,
            "description": "",
            "title": "Palm",
            "piecea": "1-melaleuca-citrina.png",
            "pieceb": "1-cor-capulin.png",
            "image": "1-melaleuca-citrina.png" },
        { 
            "qn": "12 + 12",
            "awr": "24",
            "id": "002",
            "matched": false,
            "description": "",
            "title": "Iced Tea",
            "piecea": "2-cherax-quadricarinatus.png",
            "pieceb": "2-cor-acocil-rojo.png",
            "image": "2-cherax-quadricarinatus.png" },
        { 
            "qn": "13 + 13",
            "awr": "26",
            "id": "003",
            "matched": false,
            "description": "",
            "title": "Sunglasses",
            "piecea": "3-linepithema-humile.png",
            "pieceb": "3-cor-hormiga-chicatana.png",
            "image": "3-linepithema-humile.png" },
        { 
            "qn": "14 + 14",
            "awr": "28",
            "id": "004",
            "matched": false,
            "description": "",
            "title": "Starfish",
            "piecea": "4-achatina-fulica.png",
            "pieceb": "4-cor-caracol-de-tierra.png",
            "image": "4-achatina-fulica.png" },
        { 
            "qn": "15 + 15",
            "awr": "30",
            "id": "005",
            "matched": false,
            "description": "",
            "title": "Banana",
            "piecea": "5-hemidactylus-frenatus.png",
            "pieceb": "5-cor-basilisco-rayado.png",
            "image": "5-hemidactylus-frenatus.png" },
        { 
            "qn": "16 + 16",
            "awr": "32",
            "id": "006",
            "matched": false,
            "description": "",
            "title": "Beach Ball",
            "piecea": "6-xenopus-laevis.png",
            "pieceb": "6-cor-sapo-borracho.png",
            "image": "6-xenopus-laevis.png" },
        { 
            "qn": "17 + 17",
            "awr": "34",
            "id": "007",
            "matched": false,
            "description": "",
            "title": "Ice Cream",
            "piecea": "7-sus-scrofa.png",
            "pieceb": "7-cor-pecari-de-collar.png",
            "image": "7-sus-scrofa.png" },
        { 
            "qn": "18 + 18",
            "awr": "36",
            "id": "008",
            "matched": false,
            "description": "",
            "title": "Tiki",
            "piecea": "8-myiopsitta-monachus.png",
            "pieceb": "8-cor-cotorra-serrana.png",
            "image": "8-myiopsitta-monachus.png" },
        { 
            "qn": "19 + 19",
            "awr": "38",
            "id": "009",
            "matched": false,
            "description": "",
            "title": "Dolphin",
            "piecea": "9-melinis-repens.png",
            "pieceb": "9-cor-pasto-navajita.png",
            "image": "9-melinis-repens.png" },
        { 
            "qn": "20 + 20",
            "awr": "40",
            "id": "010",
            "matched": false,
            "description": "",
            "title": "Lemon",
            "piecea": "10-carassius-auratus.png",
            "pieceb": "10-cor-mexplapique-michoacano.png",
            "image": "10-carassius-auratus.png" },
        { 
            "qn": "21 + 21",
            "awr": "42",
            "id": "011",
            "matched": false,
            "description": "",
            "title": "Flamingo",
            "piecea": "11-leonotis-nepetifolia.png",
            "pieceb": "11-cor-cempasuchil.png",
            "image": "11-leonotis-nepetifolia.png" },
        { 
            "qn": "22 + 22",
            "awr": "44",
            "id": "012",
            "matched": false,
            "description": "",
            "title": "Shack",
            "piecea": "12-undaria-pinnatifida.png",
            "pieceb": "12-cor-kelp.png",
            "image": "12-undaria-pinnatifida.png" }
    ]
}
