<?xml version="1.0" encoding="utf-8" ?><dwsync><file name="Luna-1.png" server="ixmati//usr/local/apache/htdocs-paisma/" local="3655743760" remote="3655412520" Dst="-1" /><file name="Luna-2.png" server="ixmati//usr/local/apache/htdocs-paisma/" local="3655743760" remote="3655412520" Dst="-1" /><file name="Luna-3-blank.png" server="ixmati//usr/local/apache/htdocs-paisma/" local="3655743790" remote="3655412520" Dst="-1" /><file name="Luna-3.png" server="ixmati//usr/local/apache/htdocs-paisma/" local="3655743760" remote="3655412520" Dst="-1" /><file name="Tarjeta.png" server="ixmati//usr/local/apache/htdocs-paisma/" local="3655743790" remote="3655412520" Dst="-1" /><file name="accionpositiva-blank.png" server="ixmati//usr/local/apache/htdocs-paisma/" local="3655743761" remote="3655412520" Dst="-1" /><file name="accionpositiva.png" server="ixmati//usr/local/apache/htdocs-paisma/" local="3655743790" remote="3655412520" Dst="-1" /><file name="consecuencia-blank.png" server="ixmati//usr/local/apache/htdocs-paisma/" local="3655743761" remote="3655412520" Dst="-1" /><file name="consecuencia.png" server="ixmati//usr/local/apache/htdocs-paisma/" local="3655743790" remote="3655412520" Dst="-1" /><file name="especie-blank.png" server="ixmati//usr/local/apache/htdocs-paisma/" local="3655743762" remote="3655412520" Dst="-1" /><file name="especie.png" server="ixmati//usr/local/apache/htdocs-paisma/" local="3655743790" remote="3655412520" Dst="-1" /></dwsync>